<?xml version="1.0" encoding="utf-8"?>
<TextureAtlas>
    <Texture>images\Game Boy _ GBC - Pokemon Red _ Blue - Backgrounds (Places) - Cerulean City</Texture>
    <Regions>

    // Ceruclean City Tiles
    <Region id="1" name="blue-brick" x="8" y="23" width="16" height="16"/>
    <Region id="2" name="bush-jewel-hybrid" x="88" y="71" width="16" height="16"/>
    <Region id="3" name="bush" x="88" y="87" width="16" height="16"/>
    <Region id="4" name="jewel" x="104" y="71" width="16" height="16"/>
    <Region id="5" name="water" x="104" y="87" width="16" height="16"/>
    <Region id="6" name="cylinder" x="120" y="119" width="16" height="16"/>
    <Region id="7" name="tree" x="136" y="119" width="16" height="16"/>
    <Region id="8" name="grass" x="136" y="135" width="16" height="16"/>
    <Region id="9" name="yard" x="136" y="151" width="16" height="16"/>
    <Region id="10" name="left-top-corner-roof" x="136" y="183" width="16" height="16"/>
    <Region id="11" name="left-bottom-corner-roof" x="136" y="199" width="16" height="16"/>
    <Region id="12" name="roof" x="152" y="183" width="16" height="16"/>
    <Region id="13" name="door" x="152" y="199" width="16" height="16"/>
    <Region id="14" name="right-window" x="168" y="199" width="16" height="16"/>
    <Region id="15" name="left-window" x="184" y="199" width="16" height="16"/>
    <Region id="16" name="dual-window" x="200" y="199" width="16" height="16"/>
    <Region id="17" name="right-bottom-corner-roof" x="216" y="199" width="16" height="16"/>
    <Region id="18" name="right-top-corner-roof" x="216" y="183" width="16" height="16"/>
    <Region id="19" name="left-window-right-stripe" x="248" y="199" width="16" height="16"/>
    <Region id="20" name="path-grass" x="8" y="215" width="16" height="16"/>
    <Region id="21" name="water-top-edge" x="8" y="247" width="16" height="16"/>
    <Region id="22" name="cave-entrance" x="72" y="199" width="16" height="16"/>
    <Region id="23" name="gate" x="328" y="23" width="16" height="16"/>
    <Region id="24" name="grass-gate" x="392" y="71" width="16" height="16"/>
    <Region id="25" name="path-gate" x="136" y="263" width="16" height="16"/>
    <Region id="26" name="path-fence" x="152" y="279" width="16" height="16"/>
    <Region id="27" name="grass-fence" x="168" y="279" width="16" height="16"/>
    <Region id="28" name="bottom-bubble" x="8" y="375" width="16" height="16"/>
    <Region id="29" name="top-bubble" x="8" y="391" width="16" height="16"/>
    <Region id="30" name="blank-path" x="8" y="327" width="16" height="16"/>
    <Region id="30" name="bottom-left-grass-path" x="8" y="327" width="16" height="16"/>
    <Region id="31" name="grass-left-fence" x="600" y="327" width="16" height="16"/>
    <Region id="32" name="gym-window" x="504" y="327" width="16" height="16"/>
    <Region id="33" name="bollards" x="264" y="487" width="16" height="16"/>
    <Region id="34" name="signpost" x="280" y="487" width="16" height="16"/>
    <Region id="35" name="sapling" x="312" y="471" width="16" height="16"/>
    <Region id="35" name="right-railing" x="216" y="535" width="16" height="16"/>
    <Region id="36" name="left-railing" x="200" y="535" width="16" height="16"/>
    <Region id="37" name="path-left-fence" x="520" y="327" width="16" height="16"/>
    <Region id="38" name="path-fence" x="536" y="327" width="16" height="16"/>
    <Region id="39" name="grass-right-fence" x="552" y="327" width="16" height="16"/>
    <Region id="40" name="jewel-bush-hybrid" x="88" y="199" width="16" height="16"/>
    <Region id="41" name="middle-roof" x="392" y="295" width="16" height="16"/>
    <Region id="42" name="mart-left-wall" x="200" y="422" width="16" height="16"/>
    <Region id="43" name="mart-left-wall-window" x="200" y="406" width="16" height="16"/>
    <Region id="44" name="mart-dual-window" x="216" y="406" width="16" height="16"/>
    <Region id="45" name="mart-right-wall-window" x="248" y="406" width="16" height="16"/>
    <Region id="46" name="mart-right-wall" x="248" y="390" width="16" height="16"/>
    <Region id="47" name="mart-door" x="216" y="422" width="16" height="16"/>
    <Region id="48" name="mart-sign" x="424" y="422" width="16" height="16"/>
    <Region id="49" name="mart-poke-sign" x="328" y="294" width="16" height="16"/>
    <Region id="50" name="gym-left-wall-window" x="392" y="327" width="16" height="16"/>
    <Region id="51" name="gym-right-wall-window" x="504" y="327" width="16" height="16"/>
    <Region id="52" name="gym-right-sign" x="472" y="311" width="16" height="16"/>
    <Region id="53" name="gym-left-sign" x="456" y="311" width="16" height="16"/>

    // Ceruclean City Gym Tiles
    <Region id="54" name="top-border" x="656" y="327" width="16" height="16"/>
    <Region id="55" name="blue-tile" x="656" y="343" width="16" height="16"/>
    <Region id="56" name="gym-water" x="672" y="359" width="16" height="16"/>
    <Region id="57" name="elevated-floor" x="688" y="375" width="16" height="16"/>
    <Region id="58" name="elevated-bottom-edge-floor" x="720" y="375" width="16" height="16"/>
    <Region id="58" name="top-edge-floor" x="720" y="359" width="16" height="16"/>
    <Region id="59" name="floor" x="768" y="391" width="16" height="16"/>
    <Region id="60" name="entrance" x="720" y="535" width="16" height="16"/>
    <Region id="61" name="podium" x="704" y="503" width="16" height="16"/>
    <Region id="62" name="statue" x="704" y="487" width="16" height="16"/>







    </Regions>
</TextureAtlas>
